dotcoder/__init__.py
dotcoder/coders/__init__.py
dotcoder/coders/base_coder.py
dotcoder/coders/base_prompts.py
dotcoder/coders/editblock_coder.py
dotcoder/coders/editblock_func_coder.py
dotcoder/coders/editblock_func_prompts.py
dotcoder/coders/editblock_prompts.py
dotcoder/coders/single_wholefile_func_coder.py
dotcoder/coders/single_wholefile_func_prompts.py
dotcoder/coders/wholefile_coder.py
dotcoder/coders/wholefile_func_coder.py
dotcoder/coders/wholefile_func_prompts.py
dotcoder/coders/wholefile_prompts.py
dotcoder/commands.py
dotcoder/diffs.py
dotcoder/dump.py
dotcoder/history.py
dotcoder/io.py
dotcoder/main.py
dotcoder/models/__init__.py
dotcoder/models/model.py
dotcoder/models/openai.py
dotcoder/models/openrouter.py
dotcoder/prompts.py
dotcoder/repo.py
dotcoder/repomap.py
dotcoder/sendchat.py
dotcoder/utils.py
dotcoder/versioncheck.py
dotcoder/voice.py
dotcoder-0.1.4.dist-info/LICENSE.txt
dotcoder-0.1.4.dist-info/METADATA
dotcoder-0.1.4.dist-info/WHEEL
dotcoder-0.1.4.dist-info/entry_points.txt
dotcoder-0.1.4.dist-info/RECORD
