Metadata-Version: 2.1
Name: dotcoder
Version: 0.1.4
Summary: 
Author: Your Name
Author-email: you@example.com
Requires-Python: >=3.9,<3.13
Classifier: Programming Language :: Python :: 3
Classifier: Programming Language :: Python :: 3.9
Classifier: Programming Language :: Python :: 3.10
Classifier: Programming Language :: Python :: 3.11
Requires-Dist: GitPython (==3.1.31)
Requires-Dist: PyYAML
Requires-Dist: Pygments (==2.15.1)
Requires-Dist: aiohttp (==3.8.4)
Requires-Dist: aiosignal (==1.3.1)
Requires-Dist: async-timeout (==4.0.2)
Requires-Dist: attrs (==23.1.0)
Requires-Dist: backoff (==2.2.1)
Requires-Dist: certifi (==2023.5.7)
Requires-Dist: charset-normalizer (==3.1.0)
Requires-Dist: configargparse
Requires-Dist: diskcache (==5.6.1)
Requires-Dist: frozenlist (==1.3.3)
Requires-Dist: gitdb (==4.0.10)
Requires-Dist: idna (==3.4)
Requires-Dist: jsonschema (==4.17.3)
Requires-Dist: markdown-it-py (==2.2.0)
Requires-Dist: mdurl (==0.1.2)
Requires-Dist: multidict (==6.0.4)
Requires-Dist: networkx (==3.1)
Requires-Dist: numpy (==1.24.3)
Requires-Dist: openai (==0.27.6)
Requires-Dist: prompt-toolkit (==3.0.38)
Requires-Dist: requests (==2.30.0)
Requires-Dist: rich (==13.3.5)
Requires-Dist: scipy (>=1.11.1,<2.0.0)
Requires-Dist: smmap (==5.0.0)
Requires-Dist: sounddevice (==0.4.6)
Requires-Dist: soundfile (==0.12.1)
Requires-Dist: tqdm (==4.65.0)
Requires-Dist: urllib3 (==2.0.2)
Requires-Dist: wcwidth (==0.2.6)
Requires-Dist: yarl (==1.9.2)
